biglibrary/__init__.py
biglibrary-2.0.0.dist-info/LICENSE
biglibrary-2.0.0.dist-info/METADATA
biglibrary-2.0.0.dist-info/WHEEL
biglibrary-2.0.0.dist-info/top_level.txt
biglibrary-2.0.0.dist-info/RECORD
