Metadata-Version: 2.1
Name: biglibrary
Version: 2.0.0
Summary: A package with many functions that are repeated with developers or that help improve software performance or facilitate programming.
Home-page: UNKNOWN
Author: yasserbdj96
Author-email: yasser.bdj96@gmail.com
License: MIT License
Project-URL: Source Code, https://github.com/yasserbdj96/hiphp
Project-URL: Author WebSite, https://yasserbdj96.github.io/
Project-URL: Instagram, https://www.instagram.com/yasserbdj96/
Keywords: yasserbdj96,python,biglibrary,center,lslist.
Platform: UNKNOWN
Classifier: Development Status :: 5 - Production/Stable
Classifier: Intended Audience :: Developers
Classifier: License :: OSI Approved :: MIT License
Classifier: Programming Language :: Python :: 3
Classifier: Operating System :: Unix
Classifier: Operating System :: MacOS :: MacOS X
Classifier: Operating System :: Microsoft :: Windows
Classifier: Topic :: Software Development :: Build Tools
Classifier: Topic :: Software Development :: Libraries :: Python Modules
Classifier: Topic :: Communications :: Email
Requires-Python: >=3.x.x
License-File: LICENSE
